{
  "status": "success",
  "data": {
    "parkings": {
      "AP02": {
        "description": "Parkplatz Sportgebäude",
        "vacancy": 28,
        "datestamp": "2026-01-03T20:25:11+01:00",
        "capacity": 97,
        "maintenance": false,
        "opened": true
      },
      "AP01": {
        "description": "Parkhaus Sportgebäude",
        "vacancy": 119,
        "datestamp": "2026-01-03T20:25:12+01:00",
        "capacity": 280,
        "maintenance": false,
        "opened": true
      },
      "SP02": {
        "description": "Altstadt",
        "vacancy": 288,
        "datestamp": "2026-01-03T20:24:14+01:00",
        "capacity": 456,
        "maintenance": false,
        "opened": true
      },
      "SP01": {
        "description": "am Gütsch",
        "vacancy": 88,
        "datestamp": "2026-01-03T20:25:08+01:00",
        "capacity": 100,
        "maintenance": false,
        "opened": true
      },
      "PKF": {
        "description": "Parkhaus Flora",
        "vacancy": 27,
        "datestamp": "2026-01-03T20:24:47+01:00",
        "capacity": 65,
        "maintenance": false,
        "opened": true
      },
      "NP07": {
        "description": "Schweizerhof",
        "vacancy": 130,
        "datestamp": "2026-01-03T20:24:16+01:00",
        "capacity": 250,
        "maintenance": false,
        "opened": true
      },
      "NP08": {
        "description": "Casino-Palace",
        "vacancy": 94,
        "datestamp": "2026-01-03T20:24:15+01:00",
        "capacity": 250,
        "maintenance": false,
        "opened": true
      },
      "SP06": {
        "description": "Bahnhofparking P3",
        "vacancy": 328,
        "datestamp": "2026-01-03T20:24:14+01:00",
        "capacity": 447,
        "maintenance": false,
        "opened": true
      },
      "SP05": {
        "description": "Bahnhofparking P1+P2",
        "vacancy": 219,
        "datestamp": "2026-01-03T20:24:14+01:00",
        "capacity": 453,
        "maintenance": false,
        "opened": true
      },
      "NP12": {
        "description": "Löwencenter",
        "vacancy": 215,
        "datestamp": "2026-01-03T20:24:21+01:00",
        "capacity": 345,
        "maintenance": false,
        "opened": true
      },
      "SP04": {
        "description": "Kantonalbank",
        "vacancy": 98,
        "datestamp": "2026-01-03T20:24:14+01:00",
        "capacity": 280,
        "maintenance": false,
        "opened": true
      },
      "NP11": {
        "description": "City-Parking",
        "vacancy": 369,
        "datestamp": "2026-01-03T20:23:26+01:00",
        "capacity": 450,
        "maintenance": false,
        "opened": true
      },
      "SP03": {
        "description": "Kesselturm",
        "vacancy": 230,
        "datestamp": "2026-01-03T20:22:35+01:00",
        "capacity": 340,
        "maintenance": false,
        "opened": true
      },
      "NP13": {
        "description": "Nationalhof",
        "vacancy": 89,
        "datestamp": "2026-01-03T20:24:18+01:00",
        "capacity": 220,
        "maintenance": false,
        "opened": true
      },
      "SP09": {
        "description": "Hirzenmatt",
        "vacancy": 18,
        "datestamp": "2026-01-03T20:25:11+01:00",
        "capacity": 53,
        "maintenance": false,
        "opened": true
      }
    },
    "groups": {
      "north": {
        "description": "Parkhäuser NORD",
        "vacancy": 897,
        "capacity": 1515
      },
      "messe": {
        "description": "Allmend / Messe",
        "vacancy": 147,
        "capacity": 377
      },
      "south": {
        "description": "Parkhäuser SÜD",
        "vacancy": 1269,
        "capacity": 2129
      }
    },
    "time": "2026-01-03T20:25:46+01:00"
  }
}